Workbook

Sheet Inputs
A1: FY2025 working-capital inputs (blue = source data)
A2: Source: Screener.in ratios tables (consolidated; Britannia and Colgate standalone). Sales in Rs crore.
A4: Company | B4: Ticker | C4: Sales (Rs cr) | D4: Debtor days | E4: Inventory days | F4: Payable days
A5: ITC | B5: ITC | C5: 75323 | D5: 23 | E5: 178 | F5: 55
A6: Hindustan Unilever | B6: HINDUNILVR | C6: 61328 | D6: 23 | E6: 61 | F6: 156
A7: Tata Consumer Products | B7: TATACONSUM | C7: 17618 | D7: 18 | E7: 152 | F7: 148
A8: Britannia Industries | B8: BRITANNIA | C8: 17296 | D8: 8 | E8: 39 | F8: 55
A9: Godrej Consumer Products | B9: GODREJCP | C9: 14364 | D9: 46 | E9: 79 | F9: 120
A10: Dabur India | B10: DABUR | C10: 12563 | D10: 26 | E10: 175 | F10: 215
A11: Marico | B11: MARICO | C11: 10831 | D11: 43 | E11: 93 | F11: 103
A12: Colgate-Palmolive (India) | B12: COLPAL | C12: 6040 | D12: 14 | E12: 76 | F12: 185
A13: Emami | B13: EMAMILTD | C13: 3809 | D13: 43 | E13: 94 | F13: 133

Sheet Model
A1: Cash conversion cycle and cash release to peer median
A2: Cash per day = Sales / 365. Release = days worse than peer median x cash per day (0 if already better).
A4: Company | B4: Cash per day (Rs cr) | C4: CCC (days) | D4: Cash tied up (Rs cr) | E4: Release: receivables | F4: Release: inventory | G4: Release: payables | H4: Total release (Rs cr) | I4: Biggest lever
A5: =Inputs!A5 | B5: =Inputs!C5/365 | C5: =Inputs!D5+Inputs!E5-Inputs!F5 | D5: =C5*B5 | E5: =MAX(0,Inputs!D5-MEDIAN(Inputs!D$5:Inputs!D$13))*B5 | F5: =MAX(0,Inputs!E5-MEDIAN(Inputs!E$5:Inputs!E$13))*B5 | G5: =MAX(0,MEDIAN(Inputs!F$5:Inputs!F$13)-Inputs!F5)*B5 | H5: =SUM(E5:G5) | I5: =IF(H5=0,"At/better than median",IF(E5=MAX(E5:G5),"Receivables",IF(F5=MAX(E5:G5),"Inventory","Payables")))
A6: =Inputs!A6 | B6: =Inputs!C6/365 | C6: =Inputs!D6+Inputs!E6-Inputs!F6 | D6: =C6*B6 | E6: =MAX(0,Inputs!D6-MEDIAN(Inputs!D$5:Inputs!D$13))*B6 | F6: =MAX(0,Inputs!E6-MEDIAN(Inputs!E$5:Inputs!E$13))*B6 | G6: =MAX(0,MEDIAN(Inputs!F$5:Inputs!F$13)-Inputs!F6)*B6 | H6: =SUM(E6:G6) | I6: =IF(H6=0,"At/better than median",IF(E6=MAX(E6:G6),"Receivables",IF(F6=MAX(E6:G6),"Inventory","Payables")))
A7: =Inputs!A7 | B7: =Inputs!C7/365 | C7: =Inputs!D7+Inputs!E7-Inputs!F7 | D7: =C7*B7 | E7: =MAX(0,Inputs!D7-MEDIAN(Inputs!D$5:Inputs!D$13))*B7 | F7: =MAX(0,Inputs!E7-MEDIAN(Inputs!E$5:Inputs!E$13))*B7 | G7: =MAX(0,MEDIAN(Inputs!F$5:Inputs!F$13)-Inputs!F7)*B7 | H7: =SUM(E7:G7) | I7: =IF(H7=0,"At/better than median",IF(E7=MAX(E7:G7),"Receivables",IF(F7=MAX(E7:G7),"Inventory","Payables")))
A8: =Inputs!A8 | B8: =Inputs!C8/365 | C8: =Inputs!D8+Inputs!E8-Inputs!F8 | D8: =C8*B8 | E8: =MAX(0,Inputs!D8-MEDIAN(Inputs!D$5:Inputs!D$13))*B8 | F8: =MAX(0,Inputs!E8-MEDIAN(Inputs!E$5:Inputs!E$13))*B8 | G8: =MAX(0,MEDIAN(Inputs!F$5:Inputs!F$13)-Inputs!F8)*B8 | H8: =SUM(E8:G8) | I8: =IF(H8=0,"At/better than median",IF(E8=MAX(E8:G8),"Receivables",IF(F8=MAX(E8:G8),"Inventory","Payables")))
A9: =Inputs!A9 | B9: =Inputs!C9/365 | C9: =Inputs!D9+Inputs!E9-Inputs!F9 | D9: =C9*B9 | E9: =MAX(0,Inputs!D9-MEDIAN(Inputs!D$5:Inputs!D$13))*B9 | F9: =MAX(0,Inputs!E9-MEDIAN(Inputs!E$5:Inputs!E$13))*B9 | G9: =MAX(0,MEDIAN(Inputs!F$5:Inputs!F$13)-Inputs!F9)*B9 | H9: =SUM(E9:G9) | I9: =IF(H9=0,"At/better than median",IF(E9=MAX(E9:G9),"Receivables",IF(F9=MAX(E9:G9),"Inventory","Payables")))
A10: =Inputs!A10 | B10: =Inputs!C10/365 | C10: =Inputs!D10+Inputs!E10-Inputs!F10 | D10: =C10*B10 | E10: =MAX(0,Inputs!D10-MEDIAN(Inputs!D$5:Inputs!D$13))*B10 | F10: =MAX(0,Inputs!E10-MEDIAN(Inputs!E$5:Inputs!E$13))*B10 | G10: =MAX(0,MEDIAN(Inputs!F$5:Inputs!F$13)-Inputs!F10)*B10 | H10: =SUM(E10:G10) | I10: =IF(H10=0,"At/better than median",IF(E10=MAX(E10:G10),"Receivables",IF(F10=MAX(E10:G10),"Inventory","Payables")))
A11: =Inputs!A11 | B11: =Inputs!C11/365 | C11: =Inputs!D11+Inputs!E11-Inputs!F11 | D11: =C11*B11 | E11: =MAX(0,Inputs!D11-MEDIAN(Inputs!D$5:Inputs!D$13))*B11 | F11: =MAX(0,Inputs!E11-MEDIAN(Inputs!E$5:Inputs!E$13))*B11 | G11: =MAX(0,MEDIAN(Inputs!F$5:Inputs!F$13)-Inputs!F11)*B11 | H11: =SUM(E11:G11) | I11: =IF(H11=0,"At/better than median",IF(E11=MAX(E11:G11),"Receivables",IF(F11=MAX(E11:G11),"Inventory","Payables")))
A12: =Inputs!A12 | B12: =Inputs!C12/365 | C12: =Inputs!D12+Inputs!E12-Inputs!F12 | D12: =C12*B12 | E12: =MAX(0,Inputs!D12-MEDIAN(Inputs!D$5:Inputs!D$13))*B12 | F12: =MAX(0,Inputs!E12-MEDIAN(Inputs!E$5:Inputs!E$13))*B12 | G12: =MAX(0,MEDIAN(Inputs!F$5:Inputs!F$13)-Inputs!F12)*B12 | H12: =SUM(E12:G12) | I12: =IF(H12=0,"At/better than median",IF(E12=MAX(E12:G12),"Receivables",IF(F12=MAX(E12:G12),"Inventory","Payables")))
A13: =Inputs!A13 | B13: =Inputs!C13/365 | C13: =Inputs!D13+Inputs!E13-Inputs!F13 | D13: =C13*B13 | E13: =MAX(0,Inputs!D13-MEDIAN(Inputs!D$5:Inputs!D$13))*B13 | F13: =MAX(0,Inputs!E13-MEDIAN(Inputs!E$5:Inputs!E$13))*B13 | G13: =MAX(0,MEDIAN(Inputs!F$5:Inputs!F$13)-Inputs!F13)*B13 | H13: =SUM(E13:G13) | I13: =IF(H13=0,"At/better than median",IF(E13=MAX(E13:G13),"Receivables",IF(F13=MAX(E13:G13),"Inventory","Payables")))
A15: Peer median | C15: =MEDIAN(C5:C13)
A16: Total release, all companies | H16: =SUM(H5:H13)
A17: Total release, excl. ITC | H17: =H16-SUMIF(A5:A13,"ITC",H5:H13)
A18: ITC is excluded from the headline: its leaf-tobacco stock is aged for years by design.

Sheet SCF Scenario
A1: Supply chain finance scenario
A2: Bank pays suppliers early; buyer pays the bank later, extending its payable days.
A3: Extra payable days (change me) | B3: 15
A4: Company | B4: Payable days now | C4: Payable days with SCF | D4: Cash released (Rs cr)
A5: =Inputs!A5 | B5: =Inputs!F5 | C5: =B5+$B$3 | D5: =$B$3*Model!B5
A6: =Inputs!A6 | B6: =Inputs!F6 | C6: =B6+$B$3 | D6: =$B$3*Model!B6
A7: =Inputs!A7 | B7: =Inputs!F7 | C7: =B7+$B$3 | D7: =$B$3*Model!B7
A8: =Inputs!A8 | B8: =Inputs!F8 | C8: =B8+$B$3 | D8: =$B$3*Model!B8
A9: =Inputs!A9 | B9: =Inputs!F9 | C9: =B9+$B$3 | D9: =$B$3*Model!B9
A10: =Inputs!A10 | B10: =Inputs!F10 | C10: =B10+$B$3 | D10: =$B$3*Model!B10
A11: =Inputs!A11 | B11: =Inputs!F11 | C11: =B11+$B$3 | D11: =$B$3*Model!B11
A12: =Inputs!A12 | B12: =Inputs!F12 | C12: =B12+$B$3 | D12: =$B$3*Model!B12
A13: =Inputs!A13 | B13: =Inputs!F13 | C13: =B13+$B$3 | D13: =$B$3*Model!B13
A15: Total | D15: =SUM(D5:D13)

Sheet CCC Trend
A1: Cash conversion cycle (days), FY2015-FY2025
A3: Ticker | B3: FY2015 | C3: FY2016 | D3: FY2017 | E3: FY2018 | F3: FY2019 | G3: FY2020 | H3: FY2021 | I3: FY2022 | J3: FY2023 | K3: FY2024 | L3: FY2025 | M3: Change (days)
A4: BRITANNIA | B4: -19 | C4: -16 | D4: 2 | E4: -8 | F4: -6 | G4: -6 | H4: -4 | I4: 10 | J4: -3 | K4: -9 | L4: -8 | M4: =L4-B4
A5: COLPAL | B5: -59 | C5: -54 | D5: -64 | E5: -78 | F5: -69 | G5: -62 | H5: -91 | I5: -75 | J5: -76 | K5: -113 | L5: -95 | M5: =L5-B5
A6: DABUR | B6: 16 | C6: 6 | D6: 3 | E6: 12 | F6: 18 | G6: 22 | H6: 2 | I6: 13 | J6: 14 | K6: -11 | L6: -14 | M6: =L6-B6
A7: EMAMILTD | B7: -13 | C7: -24 | D7: 12 | E7: 0 | F7: 2 | G7: 9 | H7: 9 | I7: 20 | J7: 20 | K7: 9 | L7: 4 | M7: =L7-B7
A8: GODREJCP | B8: 35 | C8: 31 | D8: 14 | E8: -20 | F8: -33 | G8: -23 | H8: 11 | I8: 31 | J8: 19 | K8: 16 | L8: 5 | M8: =L8-B8
A9: HINDUNILVR | B9: -59 | C9: -67 | D9: -85 | E9: -107 | F9: -90 | G9: -100 | H9: -83 | I9: -64 | J9: -49 | K9: -70 | L9: -72 | M9: =L9-B9
A10: ITC | B10: 181 | C10: 199 | D10: 146 | E10: 116 | F10: 121 | G10: 130 | H10: 130 | I10: 104 | J10: 104 | K10: 148 | L10: 146 | M10: =L10-B10
A11: MARICO | B11: 71 | C11: 45 | D11: 101 | E11: 107 | F11: 75 | G11: 76 | H11: 17 | I11: 30 | J11: 20 | K11: 19 | L11: 33 | M11: =L11-B11
A12: TATACONSUM | B12: 122 | C12: 129 | D12: 115 | E12: 108 | F12: 119 | G12: 86 | H12: 61 | I12: 46 | J12: 40 | K12: 26 | L12: 22 | M12: =L12-B12

Sheet Chart
